chkstyle/__init__.py
chkstyle/core.py
fastaistyle-0.0.12.dist-info/METADATA
fastaistyle-0.0.12.dist-info/WHEEL
fastaistyle-0.0.12.dist-info/entry_points.txt
fastaistyle-0.0.12.dist-info/top_level.txt
fastaistyle-0.0.12.dist-info/RECORD
