Metadata-Version: 2.4
Name: fastaistyle
Version: 0.0.12
Summary: Style checker for fast.ai coding conventions
Author-email: Jeremy Howard <j@fast.ai>
License: Apache-2.0
Project-URL: Homepage, https://github.com/AnswerDotAI/fastaistyle
Classifier: Development Status :: 4 - Beta
Classifier: Intended Audience :: Developers
Classifier: Programming Language :: Python :: 3
Requires-Python: >=3.10
Requires-Dist: tomli; python_version < "3.11"
Provides-Extra: dev
Requires-Dist: fastship; extra == "dev"
Requires-Dist: build; extra == "dev"
Requires-Dist: twine; extra == "dev"
